teststack/__init__.py
teststack/__main__.py
teststack/_version.py
teststack/git.py
teststack/utils.py
teststack/commands/containers.py
teststack/commands/environment.py
teststack/containers/docker.py
teststack/containers/podman.py
teststack-0.16.1.dist-info/licenses/LICENSE
teststack-0.16.1.dist-info/METADATA
teststack-0.16.1.dist-info/WHEEL
teststack-0.16.1.dist-info/entry_points.txt
teststack-0.16.1.dist-info/top_level.txt
teststack-0.16.1.dist-info/RECORD
