Metadata-Version: 2.4
Name: teststack
Version: 0.16.1
Summary: Manage the infrastructure for running tests against
Author-email: Daniel Wallace <daniel@gtmanfred.com>
License: APACHE-2.0
Project-URL: homepage, https://github.com/gtmanfred/teststack
Project-URL: repository, https://github.com/gtmanfred/teststack
Project-URL: documentation, https://teststack.readthedocs.org
Classifier: Development Status :: 2 - Pre-Alpha
Classifier: Topic :: Software Development :: Libraries :: Python Modules
Classifier: Topic :: Software Development :: Testing
Classifier: License :: OSI Approved :: Apache Software License
Classifier: Operating System :: OS Independent
Classifier: Programming Language :: Python :: 3.8
Classifier: Programming Language :: Python :: 3.9
Classifier: Programming Language :: Python :: 3.10
Classifier: Programming Language :: Python :: 3.11
Classifier: Programming Language :: Python :: 3.12
Requires-Python: >=3.8
License-File: LICENSE
Requires-Dist: docker
Requires-Dist: six
Requires-Dist: click
Requires-Dist: toml
Requires-Dist: jinja2
Requires-Dist: GitPython
Requires-Dist: backports.entry-points-selectable
Requires-Dist: packaging
Provides-Extra: tests
Requires-Dist: coverage[toml]>=5.4; extra == "tests"
Requires-Dist: pytest; extra == "tests"
Requires-Dist: pytest-pdb; extra == "tests"
Requires-Dist: poetry; extra == "tests"
Provides-Extra: syntax
Requires-Dist: black; extra == "syntax"
Provides-Extra: dev
Requires-Dist: tox; extra == "dev"
Provides-Extra: podman
Requires-Dist: podman; extra == "podman"
Provides-Extra: docs
Requires-Dist: sphinx; extra == "docs"
Requires-Dist: sphinx-rtd-theme; extra == "docs"
Dynamic: license-file
